README.md
setup.cfg
setup.py
src/caps/__init__.py
src/caps/__main__.py
src/caps/_initialize.py
src/caps/_metadata_schema.py
src/caps/_push.py
src/caps/_transform_data.py
src/caps/_utils.py
src/caps/_validate.py
src/caps_cli.egg-info/PKG-INFO
src/caps_cli.egg-info/SOURCES.txt
src/caps_cli.egg-info/dependency_links.txt
src/caps_cli.egg-info/entry_points.txt
src/caps_cli.egg-info/not-zip-safe
src/caps_cli.egg-info/requires.txt
src/caps_cli.egg-info/top_level.txt