Metadata-Version: 2.1
Name: caps-cli
Version: 0.3.0
Summary: UNKNOWN
Home-page: https://github.com/mintproject/ModelCatalogInsertion
Author: Dhruv Patel
Author-email: dhruvpa@isi.edu
License: Apache-2
Platform: UNKNOWN
Classifier: License :: OSI Approved :: Apache Software License
Classifier: Development Status :: 3 - Alpha
Classifier: Programming Language :: Python
Classifier: Programming Language :: Python :: 3
Classifier: Programming Language :: Python :: 3.5
Classifier: Programming Language :: Python :: 3.6
Classifier: Programming Language :: Python :: 3.7
Classifier: Intended Audience :: Science/Research
Classifier: Operating System :: Unix
Requires-Python: >=3.5.0
